wreader/__init__.py
wreader/wreader.py
wreader-0.5.dist-info/LICENSE
wreader-0.5.dist-info/METADATA
wreader-0.5.dist-info/WHEEL
wreader-0.5.dist-info/top_level.txt
wreader-0.5.dist-info/RECORD
